README.rst
setup.cfg
setup.py
sphinxcontrib/__init__.py
sphinxcontrib/redpen.py
sphinxcontrib_redpen.egg-info/PKG-INFO
sphinxcontrib_redpen.egg-info/SOURCES.txt
sphinxcontrib_redpen.egg-info/dependency_links.txt
sphinxcontrib_redpen.egg-info/namespace_packages.txt
sphinxcontrib_redpen.egg-info/not-zip-safe
sphinxcontrib_redpen.egg-info/requires.txt
sphinxcontrib_redpen.egg-info/top_level.txt