Metadata-Version: 1.1
Name: sphinxcontrib-redpen
Version: 0.0.2
Summary: Redpen validator for Sphinx
Home-page: http://github.com/shirou/sphinxcontrib-redpen
Author: WAKAYAMA Shirou
Author-email: shirou.faw@gmail.com
License: Apache
Download-URL: http://pypi.python.org/pypi/sphinxcontrib-redpen
Platform: any
Classifier: Development Status :: 4 - Beta
Classifier: Environment :: Console
Classifier: Intended Audience :: Developers
Classifier: License :: OSI Approved :: Apache Software License
Classifier: Operating System :: OS Independent
Classifier: Programming Language :: Python
Classifier: Topic :: Documentation
Classifier: Topic :: Utilities
